setup.cfg
setup.py
tests/__init__.py
tests/test_vinepy.py
vinepy/__init__.py
vinepy/api.py
vinepy/endpoints.py
vinepy/errors.py
vinepy/models.py
vinepy/utils.py
vinepy.egg-info/PKG-INFO
vinepy.egg-info/SOURCES.txt
vinepy.egg-info/dependency_links.txt
vinepy.egg-info/requires.txt
vinepy.egg-info/top_level.txt