Metadata-Version: 1.0
Name: vinepy
Version: 0.6.3
Summary: Python wrapper for the Vine Private API
Home-page: https://github.com/davoclavo/vinepy
Author: David Gomez Urquiza
Author-email: david.gurquiza@gmail.com
License: MIT
Keywords: vine library api wrapper
Platform: UNKNOWN
